aiolemmy-0.2.5.dist-info/METADATA
aiolemmy-0.2.5.dist-info/WHEEL
aiolemmy-0.2.5.dist-info/entry_points.txt
aiolemmy-0.2.5.dist-info/licenses/LICENSE
aiolemmy/.gitignore
aiolemmy/__init__.py
aiolemmy/_scm_version.py
aiolemmy/_scm_version.pyi
aiolemmy/_version.py
aiolemmy/lemmy.py
aiolemmy-0.2.5.dist-info/RECORD
