Metadata-Version: 2.1
Name: aiolemmy
Version: 0.2.5
Summary: Async Lemmy API client
Author-Email: Richard Schwab <pythonaiolemmy-fw4mjeny5w@richardschwab.de>
License: AGPL-3.0-only
Project-URL: CI: GitHub, https://github.com/Nothing4You/aiolemmy/actions
Project-URL: GitHub: repo, https://github.com/Nothing4You/aiolemmy
Project-URL: GitHub: issues, https://github.com/Nothing4You/aiolemmy/issues
Requires-Python: >=3.9
Requires-Dist: aiohttp>=3.9.3
